jentic/apitools/openapi/validator/backends/spectral/__init__.py
jentic/apitools/openapi/validator/backends/spectral/py.typed
jentic/apitools/openapi/validator/backends/spectral/rulesets/spectral.mjs
jentic_openapi_validator_spectral-1.0.0a34.dist-info/licenses/LICENSE
jentic_openapi_validator_spectral-1.0.0a34.dist-info/licenses/NOTICE
jentic_openapi_validator_spectral-1.0.0a34.dist-info/WHEEL
jentic_openapi_validator_spectral-1.0.0a34.dist-info/entry_points.txt
jentic_openapi_validator_spectral-1.0.0a34.dist-info/METADATA
jentic_openapi_validator_spectral-1.0.0a34.dist-info/RECORD
